LICENSE
README.rst
setup.cfg
setup.py
test/__init__.py
test/yamldict/__init__.py
test/yamldict/test_YamlDict.py
test/yamldict/test_YamlList.py
test/yamldict/test_YamlMissing.py
test/yamldict/test_create.py
yamldict/YamlDictClass.py
yamldict/YamlIteratorWrapper.py
yamldict/YamlListClass.py
yamldict/YamlMissing.py
yamldict/YamlNavigator.py
yamldict/__init__.py
yamldict/create_function.py
yamldict/py.typed
yamldict.egg-info/PKG-INFO
yamldict.egg-info/SOURCES.txt
yamldict.egg-info/dependency_links.txt
yamldict.egg-info/requires.txt
yamldict.egg-info/top_level.txt