Metadata-Version: 2.1
Name: yamldict
Version: 1.2.1
Summary: yamldict
Home-page: UNKNOWN
Author: Bogdan Mustiata
Author-email: bogdan.mustiata@gmail.com
License: BSD
Platform: UNKNOWN
License-File: LICENSE
